MANIFEST.in
Makefile
README
setup.py
test/__init__.py
test/__init__.pyc
test/test_bag_handling.py
test/test_collections.py
test/test_compile.py
test/test_revisions.py
test/__pycache__/test_bag_handling.cpython-27-PYTEST.pyc
test/__pycache__/test_collections.cpython-27-PYTEST.pyc
test/__pycache__/test_compile.cpython-27-PYTEST.pyc
test/__pycache__/test_revisions.cpython-27-PYTEST.pyc
tiddlywebplugins/__init__.py
tiddlywebplugins/caching.py
tiddlywebplugins.caching.egg-info/PKG-INFO
tiddlywebplugins.caching.egg-info/SOURCES.txt
tiddlywebplugins.caching.egg-info/dependency_links.txt
tiddlywebplugins.caching.egg-info/namespace_packages.txt
tiddlywebplugins.caching.egg-info/not-zip-safe
tiddlywebplugins.caching.egg-info/requires.txt
tiddlywebplugins.caching.egg-info/top_level.txt