Metadata-Version: 1.0
Name: tiddlywebplugins.caching
Version: 0.9.17
Summary: A wrapping store caching entities in memcached.
Home-page: http://pypi.python.org/pypi/tiddlywebplugins.caching
Author: Chris Dent
Author-email: cdent@peermore.com
License: UNKNOWN
Platform: Posix; MacOS X; Windows
